{
  "$schema": "http://json-schema.org/draft-07/schema#",
  "title": "Manifest Schema",
  "description": "Complete file descriptions and metadata",
  "type": "object",
  "properties": {
    "generated_date": {"type": "string", "description": "When files were generated"},
    "total_files": {"type": "integer", "description": "Number of JSON files"},
    "total_size_mb": {"type": "number", "description": "Total size in megabytes"},
    "files": {
      "type": "array",
      "items": {
        "type": "object",
        "properties": {
          "filename": {"type": "string", "description": "JSON filename"},
          "description": {"type": "string", "description": "File description"},
          "size_mb": {"type": "number", "description": "File size in megabytes"},
          "record_count": {"type": "integer", "description": "Number of records"}
        },
        "required": ["filename", "description", "size_mb"]
      }
    }
  },
  "required": ["generated_date", "total_files", "files"]
}